{"hasFrontmatter":true,"frontmatter":{"raw":"title \"Structural tables\"\nauthor {\n  name \"CentrMark Team\"\n  role \"Documentation\"\n}\ntags \"example\", \"tables\", \"layout\"\nversion 1.0.0\nstatus \"Final\"\n"},"blocks":[{"kind":"Heading","hasFrontmatter":false,"level":1,"inlines":[{"kind":"Text","text":"Structural tables"}]},{"kind":"Paragraph","hasFrontmatter":false,"inlines":[{"kind":"Text","text":"If markdown pipe-tables aren't enough (they never are), you drop down into structural tables without needing AsciiDocΓÇÖs heavy table-only syntax."}]},{"kind":"BlockDirective","hasFrontmatter":false,"fenceLen":3,"name":"table","propsRaw":"columns=\"1fr 2fr\" gap=\"1rem\" align=\"top\"","body":[{"kind":"VoidDirective","hasFrontmatter":false,"name":"row","propsRaw":""},{"kind":"BlockDirective","hasFrontmatter":false,"fenceLen":3,"name":"col","propsRaw":"span=2","body":[{"kind":"Heading","hasFrontmatter":false,"level":3,"inlines":[{"kind":"Text","text":"The API Mapping Protocol"}]},{"kind":"Paragraph","hasFrontmatter":false,"inlines":[{"kind":"Text","text":"This covers the entire mapping spec."}]}]},{"kind":"VoidDirective","hasFrontmatter":false,"name":"row","propsRaw":""},{"kind":"BlockDirective","hasFrontmatter":false,"fenceLen":3,"name":"col","propsRaw":"","body":[{"kind":"Paragraph","hasFrontmatter":false,"inlines":[{"kind":"CodeSpan","text":"GET /users"}]}]},{"kind":"BlockDirective","hasFrontmatter":false,"fenceLen":3,"name":"col","propsRaw":"","body":[{"kind":"Paragraph","hasFrontmatter":false,"inlines":[{"kind":"Text","text":"Returns a list of users.\n"}]},{"kind":"List","hasFrontmatter":false,"items":[{"markerKind":"Unordered","unorderedChar":"-","inlines":[{"kind":"Text","text":"Admin"}],"blocks":[]},{"markerKind":"Unordered","unorderedChar":"-","inlines":[{"kind":"Text","text":"Standard"}],"blocks":[{"kind":"BlockDirective","hasFrontmatter":false,"fenceLen":3,"name":"","propsRaw":"","body":[]}]}]},{"kind":"Paragraph","hasFrontmatter":false,"inlines":[{"kind":"Text","text":"CentrMark is aimed at human-readable documentation that still maps cleanly into rich UIs and stable ASTs."}]}]}]}]}